{"is_source_file": false, "format": "", "description": "", "external_files": [], "external_methods": [], "published": [], "classes": [], "methods": [], "calls": [], "search-terms": [], "state": 2, "file_id": 5, "knowledge_revision": 27, "git_revision": "9163b7aca672c38f2afedb94e68ccc4f35766dc4", "hash": "b96ed7753f33a1a60d8efb40bf117dc1", "format-version": 4, "code-base-name": "notes_app_frontend", "filename": "notes_app_frontend/src/index.css", "revision_history": [{"27": "9163b7aca672c38f2afedb94e68ccc4f35766dc4"}]}